jittoku/__init__.py
jittoku/cli/entries2json.py
jittoku/cli/json2entries.py
jittoku-0.1.0.dist-info/entry_points.txt
jittoku-0.1.0.dist-info/LICENSE
jittoku-0.1.0.dist-info/WHEEL
jittoku-0.1.0.dist-info/METADATA
jittoku-0.1.0.dist-info/RECORD
