Metadata-Version: 2.1
Name: jittoku
Version: 0.1.0
Summary: Useful scripts for QE etc.
License: MIT
Author: Koki Muraoka
Author-email: koki.muraoka@gmail.com
Requires-Python: >=3.7,<4.0
Classifier: License :: OSI Approved :: MIT License
Classifier: Programming Language :: Python :: 3
Classifier: Programming Language :: Python :: 3.7
Classifier: Programming Language :: Python :: 3.8
Classifier: Programming Language :: Python :: 3.9
Requires-Dist: ase (>=3.21.1,<4.0.0)
